gver/__init__.py
gver/src/gene.svg
gver-0.0.2.dist-info/LICENSE
gver-0.0.2.dist-info/METADATA
gver-0.0.2.dist-info/WHEEL
gver-0.0.2.dist-info/top_level.txt
gver-0.0.2.dist-info/RECORD
