Metadata-Version: 2.1
Name: gver
Version: 0.0.2
Summary: gver
Home-page: https://github.com/chunribu/gver
Author: Jian Jiang
Author-email: jianjiang.bio@gmail.com
License: MIT
Keywords: Manim
Classifier: Operating System :: POSIX :: Linux
Classifier: Operating System :: MacOS :: MacOS X
Classifier: License :: OSI Approved :: MIT License
Classifier: Programming Language :: Python :: 3
License-File: LICENSE
